zpy/__init__.py
zpy/__main__.py
zpy/decrypt.py
zpy/encrypt.py
zpy/util.py
zpy/legacy/__init__.py
zpy/legacy/decrypt.py
zpy/legacy/encrypt.py
zpy/tests/__init__.py
zpy/tests/__main__.py
zpy/tests/test_decrypt.py
zpy/tests/test_encrypt.py
zpy/tests/test_util.py
zpy/tests/legacy/__init__.py
zpy/tests/legacy/test_decrypt.py
zpy/tests/legacy/test_encrypt.py
zpy-0.4.0.dist-info/DESCRIPTION.rst
zpy-0.4.0.dist-info/METADATA
zpy-0.4.0.dist-info/RECORD
zpy-0.4.0.dist-info/WHEEL
zpy-0.4.0.dist-info/entry_points.txt
zpy-0.4.0.dist-info/metadata.json
zpy-0.4.0.dist-info/top_level.txt
